{
    "file": "./converted_json\\administratorcurdua7f4f2b3b5b93d09a4aa5890.json",
    "name": null,
    "date": null,
    "tagline": null,
    "content": "\n\n\n\n\n\n\n\n\n\n\n\n\n\n  \n\n \n  \n\n\n\n\n\n\n\n\n\n\n\n \n  \n\n\n\n\n\n\n\n  \n\n\n\n  \n\n\n\n\n \n\n\n\n\n\n\n  \n\n\n \n\n \n \n\n  \n\n\n\n\n \n\n  \n\n\n\n\n  \n  \n\n\n\n  \n\n\n  \n \n  \n\n \n\n\n\n \n  \n\n  \n\n \n  \n\n\n \n  \n\n\n\n\n  \n\n\n\n\n\n  \n\n\n  \n\n\n\n\n  \n  \n\n  \n\n\n\n \n  \n\n\n\n \n\n\n\n \n\n\n \n\n\n \n\n\n \n\n \n\n\n\n\n\n\n\n\n\n\n\n\n\n\n\n\n\n\n\n\n\n\n\n\n\n\n\n\n\n\n\n\n\n\n\n\n\n\n\n\n\n\n\n\n\n\n\n\n\n\n\n\n\n\n\n\n\n\n\n\n\n\n\n\n\n\n\n\n\n\n\n\n\n\n\n\n\n\n\n\n\n\n\n\n   \n \n\n\n\n\n  \n\n\n\n\n \n \n\n  \n\n  \n\n  \n\n\n\n\n \n\n\n\n\n\n\n\n  \n \n  \n\n\n\n\n \n\n\n\n\n\n\n  \n\n \n\n\n\n \n\n\n\n\n\n\n\n\n\n\n\n\n\n\n\n\n\n\n \n\n \n\n\n\n\n  \n\n\n\n\n  \n\n\n\n\n\n\n\n\n\n\n\n\n  \n\n\n\n\n\n\n\n\n\n\n\n\n\n\n\n\n\n\n\n  \n\n\n\n\n\n\n\n \n\n\n\n\n\n\n  \n\n\n\n \n\n\n\n\n\n \n\n\n\n\n\n  \n\n\n\n\n\n  \n\n\n\n\n\n\n  \n \n\n\n\n\n  \n\n\n\n\n\n  \n\n\n  \n\n\n\n\n\n\n\n\n\n \n\n\n\n  \n\n\n\n\n \n\n\n\n\n\n \n\n\n\n\n\n \n\n\n\n\n\n\n\n\n\n\n\n  \n\n\n\n\n  \n\n\n\n\n\n  \n\n\n\n\n\n\n   \n\n\n\n\n\n\n\n\n\n\n\n\n\n\n\n\n\n\n \n\n\n\n\n\n\n\n\n\n\n  \n\n\n\n\n\n \n\n\n\n\n\n\n\n\n\n\n\n\n\n\n\n\n\n\n\n\n \n\n\n\n\n\n\n\n\n\n\n\n\n\n\n\n\n\n\n\n\n   \n\n\n\n \n\n\n\n\n\n\n\n\n\n\n \n\n\n\n \n \n\n\n\n  \n\n\n\n\n\n\n  \n\n\n\n\n\n\n\n\n\n\n\n\n\n\n\n\n\n\n  \n\n\n\n\n\n \n\n\n\n\n\n\n  \n\n\n\n\n  \n \n\n\n\n\n\n\n\n\n\n\n  \n\n\n\n\n\n\n\n\n  \n\n\n\n\n\n \n\n\n \n\n\n\n\n \n\n  \n\n\n\n  \n\n  \n\n\n\n\n\n  \n\n\n  \n\n\n\n \n\n\n\n\n\n\n\n\n\n\n \n\n\n\n\n\n  \n\n\n\n \n\n\n\n\n\n\n\n  \n\n\n\n  \n\n\n\n\n\n  \n\n\n\n\n  \n\n\n  \n\n\n\n\n\n\n\n\n\n\n\n  \n\n\n\n\n\n\n\n\n  \n\n\n  \n\n\n\n  \n\n\n\n\n\n\n  \n\n\n\n\n\n \n\n\n\n\n\n\n\n\n\n\n\n\n \n\n\n\n\n\n  \n\n\n\n\n\n\n\n \n\n\n\n\n\n \n\n\n\n\n\n\n \n\n\n\n\n\n\n\n\n\n\n\n\n  \n\n\n\n\n\n  \n\n\n\n\n\n\n \n\n\n\n\n\n\n\n\n  \n\n\n\n\n  \n\n\n\n\n\n\n  \n\n\n\n\n\n\n\n \n\n\n\n\n\n\n \n\n\n\n\n\n  \n\n\n\n \n\n\n\n\n\n\n\n\n\n\n\n\n\n\n\n\n\n\n\n\n\n\n\n   \n\n \n\n\n\n \n\n\n\n\n\n\n  \n\n\n\n\n\n  \n\n\n\n\n  \n\n\n\n\n\n\n\n\n\n \n\n\n\n\n\n\n\n\n\n\n\n\n\n\n\n\n \n\n\n\n\n\n  \n  \n\n\n\n\n \n\n\n\n\n\n \n\n\n \n\n\n\n\n\n\n\n   \n\n\n \n\n\n\n\n\n\n\n\n\n\n\n\n\n\n \n\n\n  \n\n\n\n\n\n\n  \n\n\n\n\n\n\n\n\n\n  \n\n\n\n\n\n\n\n \n\n\n\n\n\n  \n\n\n\n\n\n\n \n \n\n\n\n\n\n\n\n\n\n\n \n\n\n\n\n\n\n\n\n\n\n\n\n \n\n\n\n\n\n\n\n\n\n\n\n\n\n   \n \n \n\n\n\n\n\n\n\n\n\n\n\n\n\n\n\n\n\n\n\n\n\n\n\n\n\n\n\n\n\n\n\n\n \n\n\n\n\n\n\n\n\n\n\n\n\n\n\n \n\n\n\n\n\n\n\n\n\n\n\n\n\n\n\n\n\n\n\n\n \n\n\n\n\n\n\n\n\n\n\n \n\n\n\n\n\n\n\n\n\n\n\n\n \n\n\n \n \n\n\n\n\n\n\n\n\n   \n\n \n\n\n\n\n\n\n \n\n\n\n\n\n\n\n\n\n\n\n\n\n  \n\n\n\n\n\n\n  \n\n\n  \n\n\n  \n\n\n\n  \n\n\n\n\n\n\n\n\n \n\n\n\n\n\n  \n\n  \n\n\n\n \n\n\n\n\n \n \n\n\n\n\n\n\n\n\n\n\n\n  \n\n\n\n\n \n \n\n\n\n  \n  \n\n  \n\n\n  \n\n\n\n\n\n\n \n\n\n\n \n\n\n\n\n\n \n\n\n\n\n\n  \n\n\n  \n\n\n\n \n\n\n\n\n  \n   \n\n\n\n\n\n\n\n\n\n\n\n\n\n\n  \n\n\n\n\n\n\n\n\n\n \n\n\n\n\n \n\n\n\n\n\n  \n \n\n\n\n\n\n\n\n\n\n\n\n\n\n\n\n \n\n\n\n\n\n\n\n\n\n\n\n\n\n \n\n\n\n\n\n\n\n\n\n  \n\n\n\n\n\n\n\n\n\n  \n\n\n\n\n  \n \n\n\n  \n\n\n\n\n\n  \n\n\n\n\n \n\n\n\n\n\n\n\n \n\n\n\n\n \n\n\n\n\n\n\n\n \n\n\n\n\n \n\n\n\n\n\n  \n\n\n\n\n \n\n\n\n\n \n\n\n \n\n\n\n\n\n\n\n\n\n\n\n\n   \n\n\n\n\n \n \n\n\n\n\n\n\n  \n\n\n\n\n\n\n\n \n\n\n\n\n\n \n\n\n\n \n\n\n\n\n\n\n\n  \n\n\n\n\n\n\n\n\n  \n \n\n\n\n\n\n\n\n\n\n\n\n\n\n\n\n \n\n\n\n\n\n\n\n\n\n\n\n\n\n\n\n\n   \n\n\n\n\n\n\n\n\n\n\n\n\n\n\n\n\n\n\n\n\n\n\n\n\n\n\n\n \n\n\n\n\n\n\n\n\n\n\n\n\n\n\n\n\n\n\n\n\n\n\n\n   \n\n\n\n\n\n\n\n\n\n\n\n\n\n\n\n\n\n\n\n\n\n\n\n\n\n  \n\n\n\n  \n\n\n \n\n\n\n\n\n\n\n\n\n  \n\n\n\n\n\n\n\n\n\n\n\n\n\n\n\n\n\n\n\n\n\n\n\n\n\n\n \n\n \n\n\n\n\n\n\n\n\n\n\n\n\n\n\n\n\n\n\n\n   \n\n\n\n\n\n\n\n\n\n\n  \n\n\n\n\n\n \n\n\n\n\n\n\n\n\n\n\n\n\n\n\n\n\n\n \n\n  \n\n\n\n\n  \n\n\n\n\n\n\n\n\n\n  \n\n\n\n\n\n\n\n  \n\n\n\n\n  \n\n  \n\n\n\n\n\n\n\n\n\n \n\n\n\n\n\n\n \n\n\n\n\n\n\n\n\n\n\n\n\n\n\n  \n\n\n  \n\n\n\n\n  \n\n  \n\n\n\n  \n\n\n  \n\n\n\n\n\n \n\n\n\n\n\n\n\n\n\n\n\n\n\n\n\n\n\n\n\n\n   \n\n\n\n\n\n\n\n\n  \n\n \n\n\n\n\n\n\n\n\n\n \n\n\n\n\n\n\n\n\n\n\n\n\n\n\n\n\n\n\n\n\n  \n\n\n  \n\n\n  \n\n\n\n\n\n\n \n\n\n\n\n\n \n\n\n\n\n\n\n  \n\n\n\n\n\n\n\n\n\n\n \n\n\n\n\n\n\n\n\n\n\n\n\n\n\n\n\n\n\n\n\n\n\n\n\n\n  \n\n\n\n \n \n\n\n\n\n\n  \n\n\n\n\n\n\n   \n\n\n\n\n\n\n\n\n\n\n\n\n \n\n\n\n\n\n\n\n\n\n\n\n\n \n\n\n\n\n\n\n\n  \n \n\n\n\n\n\n\n\n\n\n\n\n\n\n\n\n\n\n\n\n\n\n\n\n\n\n\n\n\n\n\n\n \n\n\n\n\n\n\n\n\n\n\n\n\n\n\n   \n\n\n\n\n\n  \n\n\n\n  \n\n\n\n\n \n\n\n\n\n\n\n\n\n\n\n \n\n\n\n\n \n\n\n    \n \n\n\n\n\n\n\n\n\n\n\n\n \n\n\n\n \n\n\n\n\n\n \n \n\n\n \n \n\n\n\n\n\n  \n\n\n\n  \n\n\n\n \n\n\n\n\n\n\n\n\n\n\n\n\n\n\n\n\n\n\n\n\n\n\n\n\n\n\n\n  \n\n\n\n\n\n\n\n \n\n\n\n\n\n\n\n  \n\n\n\n\n\n\n\n\n\n  \n\n \n\n\n\n\n\n\n\n\n\n\n\n  \n\n  \n  \n\n\n\n\n\n\n\n  \n\n\n\n\n\n\n  \n\n\n\n\n\n\n\n\n\n\n\n\n  \n\n\n\n\n \n\n\n\n\n\n\n\n  \n\n\n\n\n\n\n\n\n \n\n\n\n\n\n\n\n\n\n\n \n\n\n\n\n\n\n\n\n \n\n \n\n\n \n\n\n\n\n  \n\n\n\n\n\n \n\n\n\n\n  \n\n\n  \n\n\n\n\n\n\n\n\n \n\n\n\n\n\n\n\n\n\n\n\n \n\n\n\n\n\n  \n\n \n\n\n\n\n\n\n\n\n\n\n\n\n\n\n\n\n\n\n\n\n\n\n\n\n\n\n\n\n \n\n\n\n\n\n\n\n\n\n\n\n\n\n \n\n\n\n\n\n  \n \n\n\n\n\n\n\n\n  \n\n\n\n\n\n\n\n\n\n\n\n\n\n\n\n\n\n\n\n\n\n\n\n\n  \n\n\n\n\n\n\n\n\n\n\n\n\n\n\n\n\n\n\n\n\n\n\n\n\n\n   \n\n\n\n\n\n\n  \n\n\n  \n\n\n\n\n\n\n\n  \n\n\n\n  \n\n\n\n \n\n\n\n \n\n\n\n\n\n\n\n  \n  \n\n  \n\n\n\n\n\n\n\n  \n \n\n\n\n\n\n\n\n\n\n\n\n \n\n\n\n\n\n\n\n\n\n\n\n\n\n\n\n\n\n\n\n\n\n\n\n\n\n\n\n\n\n\n  \n\n\n\n\n\n\n\n\n\n\n\n\n\n\n\n\n\n\n\n\n\n\n\n\n\n\n\n\n\n\n\n \n\n\n\n\n\n\n\n\n\n\n\n\n\n  \n\n\n\n\n\n\n\n\n  \n\n\n\n\n\n\n\n\n\n\n\n \n\n\n\n\n\n\n\n\n\n\n\n\n\n\n\n\n\n \n\n\n\n\n  \n\n\n\n\n\n \n\n\n\n\n  \n\n\n\n\n\n\n\n \n\n\n\n\n\n\n\n\n\n \n\n\n\n\n\n \n\n\n\n\n\n \n\n\n\n\n\n\n\n\n\n\n\n\n\n\n\n\n\n\n\n \n\n\n\n\n\n \n\n\n\n\n\n \n\n\n\n\n\n\n \n\n\n\n\n\n\n\n\n \n\n\n\n  \n\n\n\n\n\n \n\n\n\n\n\n\n\n\n \n\n\n\n  \n\n\n\n\n\n \n\n\n\n\n\n\n\n \n\n\n\n\n\n\n\n\n\n\n\n\n\n\n\n\n\n\n\n\n\n\n\n\n\n\n\n\n\n\n\n\n\n\n\n\n\n\n\n\n\n\n \n\n\n\n\n\n\n \n\n ] \n\n\n\n  \n\n ]  \n\n\n  \n\n \n\n\n \n\n\n \n\n\n  \n\n\n\n\n\n \n\n\n\n\n  \n\n\n\n\n\n\n\n\n\n\n \n\n\n\n ]\n\n\n\n\n\n\n\n\n\n\n\n\n\n \n\n\n\n\n\n  \n\n\n\n\n\n\n  \n\n\n\n\n\n ] \n\n \n\n\n\n\n\n  \n\n\n\n\n\n\n \n \n\n\n\n  \n\n\n\n\n\n\n\n\n\n\n\n\n\n\n \n\n\n\n\n\n\n\n\n\n \n\n\n\n\n\n  \n\n\n\n  \n  \n\n\n\n  \n\n  \n\n\n\n\n  \n\n\n\n\n \n\n\n\n\n\n \n\n\n\n\n\n \n\n\n\n\n\n\n\n\n\n  \n\n\n\n\n\n  \n\n\n\n  \n\n\n\n\n\n\n  \n\n\n\n\n\n \n\n\n\n\n\n\n\n\n\n\n\n\n\n  \n\n\n \n\n\n  \n\n\n\n\n\n\n\n\n\n\n\n\n\n\n  \n\n\n\n\n\n  \n\n\n\n  \n\n\n\n\n\n\n \n\n\n\n\n\n\n\n\n\n\n\n\n\n\n\n\n\n\n\n \n\n\n\n\n\n\n\n\n\n\n\n\n\n\n\n\n\n \n\n\n\n\n\n\n\n\n\n\n\n\n\n\n \n\n\n\n \n\n \n\n\n\n \n\n\n\n\n\n\n\n\n\n\n\n\n\n\n\n  \n\n\n\n  \n\n\n\n\n\n  \n\n\n\n\n\n\n\n ] \n\n\n\n  \n\n ]   \n\n\n\n  \n  \n\n\n  \n\n\n\n\n\n\n\n \n\n\n\n\n\n\n\n\n \n\n\n\n\n\n\n\n\n\n \n\n\n\n\n  \n\n\n\n\n\n \n\n\n\n\n\n\n\n \n\n\n\n\n\n\n\n\n\n  \n\n\n \n\n\n\n\n\n\n\n\n\n\n\n\n\n\n\n\n\n  \n\n\n  \n\n\n\n\n\n \n"
}